datasets_toolbox/__init__.py
datasets_toolbox/cli/__init__.py
datasets_toolbox/cli/cli.py
datasets_toolbox/cli/utils.py
datasets_toolbox/cli/commands/__init__.py
datasets_toolbox/cli/commands/import_data.py
datasets_toolbox/cli/commands/inspect/__init__.py
datasets_toolbox/cli/commands/modify/__init__.py
datasets_toolbox/cli/commands/modify/resample.py
datasets_toolbox/cli/commands/modify/slice.py
datasets_toolbox/cli/commands/modify/sync.py
datasets_toolbox/cli/commands/modify/transcribe.py
datasets_toolbox-0.1.0.dist-info/LICENSE
datasets_toolbox-0.1.0.dist-info/METADATA
datasets_toolbox-0.1.0.dist-info/WHEEL
datasets_toolbox-0.1.0.dist-info/entry_points.txt
datasets_toolbox-0.1.0.dist-info/top_level.txt
datasets_toolbox-0.1.0.dist-info/RECORD
