Metadata-Version: 2.1
Name: datasets-toolbox
Version: 0.1.0
Summary: A toolbox for audio dataset processing and augmentation.
License: MIT
Project-URL: homepage, https://github.com/JacobLinCool/datasets-toolbox
Project-URL: repository, https://github.com/JacobLinCool/datasets-toolbox
Keywords: datasets,CLI,audio
Requires-Python: >=3.9
License-File: LICENSE
Requires-Dist: click
Requires-Dist: datasets
Requires-Dist: librosa
Requires-Dist: soundfile
Requires-Dist: numpy
Requires-Dist: transformers
Requires-Dist: accelerate
Requires-Dist: torch
Requires-Dist: tqdm
